scrapyrt/__init__.py
scrapyrt/cmdline.py
scrapyrt/core.py
scrapyrt/log.py
scrapyrt/resources.py
scrapyrt/utils.py
scrapyrt/conf/__init__.py
scrapyrt/conf/default_settings.py
scrapyrt/conf/spider_settings.py
scrapyrt-0.17.0.dist-info/METADATA
scrapyrt-0.17.0.dist-info/WHEEL
scrapyrt-0.17.0.dist-info/entry_points.txt
scrapyrt-0.17.0.dist-info/licenses/LICENSE
scrapyrt-0.17.0.dist-info/RECORD
