Metadata-Version: 2.4
Name: scrapyrt
Version: 0.17.0
Summary: Put Scrapy spiders behind an HTTP API
Project-URL: Documentation, https://scrapyrt.readthedocs.io/en/latest/index.html
Project-URL: Source, https://github.com/scrapinghub/scrapyrt
Project-URL: Tracker, https://github.com/scrapinghub/scrapyrt/issues
Project-URL: Release notes, https://scrapyrt.readthedocs.io/en/latest/changes.html
Author-email: Scrapinghub <opensource@zyte.com>
Maintainer-email: Scrapinghub <opensource@zyte.com>
License-Expression: BSD-3-Clause
License-File: LICENSE
Classifier: Development Status :: 5 - Production/Stable
Classifier: Environment :: Console
Classifier: Environment :: No Input/Output (Daemon)
Classifier: Framework :: Scrapy
Classifier: Intended Audience :: Developers
Classifier: Operating System :: OS Independent
Classifier: Programming Language :: Python
Classifier: Programming Language :: Python :: 3
Classifier: Programming Language :: Python :: 3.9
Classifier: Programming Language :: Python :: 3.10
Classifier: Programming Language :: Python :: 3.11
Classifier: Programming Language :: Python :: 3.12
Classifier: Programming Language :: Python :: 3.13
Classifier: Topic :: Internet :: WWW/HTTP
Classifier: Topic :: Software Development :: Libraries :: Application Frameworks
Classifier: Topic :: Software Development :: Libraries :: Python Modules
Requires-Python: >=3.9
Requires-Dist: packaging>=20.0
Requires-Dist: scrapy>=2.7
